{
  "indexes": [
    {
      "collectionGroup": "forumPosts",
      "queryScope": "COLLECTION",
      "fields": [
        {
          "fieldPath": "tags",
          "arrayConfig": "CONTAINS"
        },
        {
          "fieldPath": "timestamp",
          "order": "DESCENDING"
        }
      ]
    },
    {
      "collectionGroup": "forumPosts",
      "queryScope": "COLLECTION",
      "fields": [
        {
          "fieldPath": "authorId",
          "order": "ASCENDING"
        },
        {
          "fieldPath": "timestamp",
          "order": "DESCENDING"
        }
      ]
    }
  ],
  "fieldOverrides": []
}